static_thumbnails/__init__.py
static_thumbnails/apps.py
static_thumbnails/get_version.py
static_thumbnails/models.py
static_thumbnails/templatetags/__init__.py
static_thumbnails/templatetags/static_thumbnails.py
static_thumbnails-0.9.dist-info/LICENSE
static_thumbnails-0.9.dist-info/METADATA
static_thumbnails-0.9.dist-info/WHEEL
static_thumbnails-0.9.dist-info/top_level.txt
static_thumbnails-0.9.dist-info/RECORD
