Metadata-Version: 2.1
Name: static-thumbnails
Version: 0.9
Summary: Extension to easy_thumbnails for Django providing thumbnails from static files
Home-page: https://github.com/mawilmsen/static-thumbnails
Author: Marc-Alexander Wilmsen
Author-email: wilmsen@valloc.de
License: UNKNOWN
Platform: any
Classifier: Development Status :: 5 - Production/Stable
Classifier: Environment :: Web Environment
Classifier: Framework :: Django
Classifier: Framework :: Django :: 2.0
Classifier: Framework :: Django :: 2.1
Classifier: Framework :: Django :: 2.2
Classifier: Intended Audience :: Developers
Classifier: License :: OSI Approved :: MIT License
Classifier: Operating System :: OS Independent
Classifier: Programming Language :: Python
Classifier: Programming Language :: Python :: 3.4
Classifier: Programming Language :: Python :: 3.5
Classifier: Programming Language :: Python :: 3.6
Classifier: Programming Language :: Python :: 3.7
Classifier: Topic :: Software Development :: Libraries :: Application Frameworks
Classifier: Topic :: Software Development :: Libraries :: Python Modules
Requires-Dist: django (>=1.8) ; python_version >= "3"
Requires-Dist: pillow ; python_version >= "3"
Requires-Dist: easy-thumbnails ; python_version >= "3"
